LICENSE
skanr/cli.py
skanr-0.0.2.dist-info/entry_points.txt
skanr-0.0.2.dist-info/LICENSE
skanr-0.0.2.dist-info/WHEEL
skanr-0.0.2.dist-info/METADATA
skanr-0.0.2.dist-info/RECORD
