Metadata-Version: 2.1
Name: skanr
Version: 0.0.2
Summary: Multithreaded IPV4 port scanner written in python
Home-page: https://github.com/madeinoz67/skanr
License: MIT
Keywords: portscanner,security
Author: Stephen Eaton
Author-email: seaton@strobotics.com.au
Requires-Python: >=3.7
Classifier: Environment :: Console
Classifier: Intended Audience :: Developers
Classifier: Intended Audience :: Information Technology
Classifier: Intended Audience :: System Administrators
Classifier: License :: OSI Approved :: MIT License
Classifier: Operating System :: OS Independent
Classifier: Programming Language :: Python
Classifier: Programming Language :: Python :: 3
Classifier: Programming Language :: Python :: 3.7
Classifier: Programming Language :: Python :: 3.8
Classifier: Programming Language :: Python :: 3.9
Classifier: Topic :: Security
Classifier: Topic :: System :: Systems Administration
Classifier: Topic :: Utilities
Requires-Dist: argparse (>=1.4.0,<2.0.0)
Requires-Dist: ipaddress (>=1.0.23,<2.0.0)
Project-URL: Repository, https://github.com/madeinoz67/skanr
